uaal_core/__init__.py
uaal_core-0.1.3.dist-info/METADATA
uaal_core-0.1.3.dist-info/WHEEL
uaal_core-0.1.3.dist-info/top_level.txt
uaal_core-0.1.3.dist-info/RECORD
