Metadata-Version: 2.4
Name: uaal-core
Version: 0.1.3
Summary: UAAL core decision ledger library
Project-URL: repository, https://github.com/LOLA0786/UAAL
Requires-Python: >=3.9
